2023/tpVerilogISL/DFlipFlop/flip_flop_d.v
module flip_flop_d(D, CLK, Q);

output reg Q;
input D, CLK;

always @(posedge CLK) 
begin
    Q = D;
end


endmodule

tpVerilogISL/DFlipFlop/flip_flop_d_tb.v
`timescale 1ns/1ns
`include "flip_flop_d.v"

module flip_flop_d_tb;

reg D = 0, CLK = 0;
wire Q;

flip_flop_d ffd(D, CLK, Q);

always begin
    CLK = ~CLK;
    #10;
end

initial begin
    $dumpfile("flip_flop_d.vcd");
    $dumpvars(0, flip_flop_d_tb);

    repeat (5) begin

        D = ~D;
        #25;

    end

    $finish;
end

endmodule

tpVerilogISL/DFlipFlop/flip_flop_d.vcd
$date
	Fri Dec  8 20:25:02 2023
$end
$version
	Icarus Verilog
$end
$timescale
	1ns
$end
$scope module flip_flop_d_tb $end
$var wire 1 ! Q $end
$var reg 1 " CLK $end
$var reg 1 # D $end
$scope module ffd $end
$var wire 1 " CLK $end
$var wire 1 # D $end
$var reg 1 ! Q $end
$upscope $end
$upscope $end
$enddefinitions $end
#0
$dumpvars
1#
1"
1!
$end
#10
0"
#20
1"
#25
0#
#30
0"
#40
0!
1"
#50
0"
1#
#60
1!
1"
#70
0"
#75
0#
#80
0!
1"
#90
0"
#100
1!
1"
1#
